[
  {
    "id": 1,
    "title": "Fantastic Soft Gloves",
    "price": 538,
    "description": "The automobile layout consists of a front-engine design, with transaxle-type transmissions mounted at the rear of the engine and four wheel drive",
    "category": "Books",
    "images": [
      "https://loremflickr.com/640/480?lock=4772712815788032",
      "https://loremflickr.com/640/480?lock=649888257802240",
      "https://loremflickr.com/640/480?lock=5324673852112896",
      "https://picsum.photos/seed/tliw9jVKbp/640/480",
      "https://loremflickr.com/640/480?lock=7731511734304768"
    ],
    "createdAt": "2024-12-14T17:19:17.803Z",
    "updatedAt": "2025-04-11T05:45:49.306Z"
  },
  {
    "id": 2,
    "title": "Ergonomic Plastic Sausages",
    "price": 386,
    "description": "Boston's most advanced compression wear technology increases muscle oxygenation, stabilizes active muscles",
    "category": "Books",
    "images": [
      "https://picsum.photos/seed/woQ5jXG/640/480",
      "https://picsum.photos/seed/nvq5my1N/640/480"
    ],
    "createdAt": "2024-08-23T01:12:15.118Z",
    "updatedAt": "2025-02-01T04:04:05.644Z"
  },
  {
    "id": 3,
    "title": "Elegant Steel Sausages",
    "price": 926,
    "description": "The beautiful range of Apple Naturalé that has an exciting mix of natural ingredients. With the Goodness of 100% Natural Ingredients",
    "category": "Beauty & Personal Care",
    "images": [
      "https://loremflickr.com/640/480?lock=2768318968627200",
      "https://loremflickr.com/640/480?lock=1287284475297792",
      "https://loremflickr.com/640/480?lock=4581552277159936",
      "https://loremflickr.com/640/480?lock=7780041454780416",
      "https://picsum.photos/seed/WaIoWRIn1Z/640/480"
    ],
    "createdAt": "2024-06-16T09:45:10.861Z",
    "updatedAt": "2024-11-29T03:29:05.057Z"
  },
  {
    "id": 4,
    "title": "Fantastic Plastic Hat",
    "price": 63,
    "description": "The automobile layout consists of a front-engine design, with transaxle-type transmissions mounted at the rear of the engine and four wheel drive",
    "category": "Clothing",
    "images": [
      "https://picsum.photos/seed/ATr8PKv/640/480",
      "https://picsum.photos/seed/2PvXEVz/640/480",
      "https://loremflickr.com/640/480?lock=4848680045641728"
    ],
    "createdAt": "2025-04-22T01:40:42.278Z",
    "updatedAt": "2025-04-25T11:59:48.239Z"
  },
  {
    "id": 5,
    "title": "Refined Steel Shoes",
    "price": 668,
    "description": "Andy shoes are designed to keeping in mind durability as well as trends, the most stylish range of shoes & sandals",
    "category": "Office Supplies",
    "images": [
      "https://picsum.photos/seed/dlMj4/640/480",
      "https://loremflickr.com/640/480?lock=8913890255568896",
      "https://picsum.photos/seed/ZToU0Bu/640/480"
    ],
    "createdAt": "2024-11-09T01:21:23.300Z",
    "updatedAt": "2025-03-21T00:02:17.281Z"
  },
  {
    "id": 6,
    "title": "Refined Rubber Computer",
    "price": 978,
    "description": "The beautiful range of Apple Naturalé that has an exciting mix of natural ingredients. With the Goodness of 100% Natural Ingredients",
    "category": "Health & Wellness",
    "images": [
      "https://picsum.photos/seed/AN180Xd/640/480",
      "https://picsum.photos/seed/0B2fYp2nd6/640/480",
      "https://loremflickr.com/640/480?lock=6028911236349952"
    ],
    "createdAt": "2024-09-26T08:29:06.711Z",
    "updatedAt": "2025-03-06T19:52:35.371Z"
  },
  {
    "id": 7,
    "title": "Generic Granite Salad",
    "price": 726,
    "description": "Carbonite web goalkeeper gloves are ergonomically designed to give easy fit",
    "category": "Automotive",
    "images": [
      "https://loremflickr.com/640/480?lock=3420324909547520",
      "https://picsum.photos/seed/pShrW/640/480",
      "https://loremflickr.com/640/480?lock=8957786310311936"
    ],
    "createdAt": "2025-01-20T07:08:25.300Z",
    "updatedAt": "2025-03-05T01:00:02.188Z"
  },
  {
    "id": 8,
    "title": "Modern Bronze Fish",
    "price": 808,
    "description": "The slim & simple Maple Gaming Keyboard from Dev Byte comes with a sleek body and 7- Color RGB LED Back-lighting for smart functionality",
    "category": "Toys & Games",
    "images": [
      "https://picsum.photos/seed/45PLCL/640/480",
      "https://loremflickr.com/640/480?lock=7931520526319616",
      "https://loremflickr.com/640/480?lock=491374606548992",
      "https://loremflickr.com/640/480?lock=4305181510467584"
    ],
    "createdAt": "2024-06-07T02:35:47.697Z",
    "updatedAt": "2024-10-21T06:00:08.654Z"
  },
  {
    "id": 9,
    "title": "Refined Metal Bike",
    "price": 510,
    "description": "Boston's most advanced compression wear technology increases muscle oxygenation, stabilizes active muscles",
    "category": "Home & Kitchen",
    "images": [
      "https://loremflickr.com/640/480?lock=3615455713427456"
    ],
    "createdAt": "2024-09-18T06:57:22.691Z",
    "updatedAt": "2024-10-18T20:32:53.957Z"
  },
  {
    "id": 10,
    "title": "Ergonomic Wooden Shoes",
    "price": 490,
    "description": "New ABC 13 9370, 13.3, 5th Gen CoreA5-8250U, 8GB RAM, 256GB SSD, power UHD Graphics, OS 10 Home, OS Office A & J 2016",
    "category": "Toys & Games",
    "images": [
      "https://loremflickr.com/640/480?lock=642971225554944"
    ],
    "createdAt": "2025-03-18T18:27:08.157Z",
    "updatedAt": "2025-03-30T21:25:40.854Z"
  },
  {
    "id": 11,
    "title": "Licensed Wooden Sausages",
    "price": 961,
    "description": "Ergonomic executive chair upholstered in bonded black leather and PVC padded seat and back for all-day comfort and support",
    "category": "Office Supplies",
    "images": [
      "https://picsum.photos/seed/BRS1YLZI/640/480",
      "https://picsum.photos/seed/WARVvCRN/640/480",
      "https://loremflickr.com/640/480?lock=7938822853623808",
      "https://picsum.photos/seed/6bc4S/640/480"
    ],
    "createdAt": "2025-03-19T03:07:23.071Z",
    "updatedAt": "2025-04-12T15:07:08.108Z"
  },
  {
    "id": 12,
    "title": "Intelligent Plastic Ball",
    "price": 620,
    "description": "Ergonomic executive chair upholstered in bonded black leather and PVC padded seat and back for all-day comfort and support",
    "category": "Sports & Outdoors",
    "images": [
      "https://loremflickr.com/640/480?lock=87577084297216",
      "https://loremflickr.com/640/480?lock=7594324206288896",
      "https://picsum.photos/seed/NhQ8ZyD8Z/640/480"
    ],
    "createdAt": "2025-03-13T09:01:22.940Z",
    "updatedAt": "2025-05-09T21:22:34.995Z"
  },
  {
    "id": 13,
    "title": "Awesome Plastic Mouse",
    "price": 686,
    "description": "Carbonite web goalkeeper gloves are ergonomically designed to give easy fit",
    "category": "Beauty & Personal Care",
    "images": [
      "https://loremflickr.com/640/480?lock=3121448004616192",
      "https://loremflickr.com/640/480?lock=6977522476515328",
      "https://loremflickr.com/640/480?lock=6902669549502464"
    ],
    "createdAt": "2024-10-05T09:12:03.046Z",
    "updatedAt": "2025-05-02T04:55:51.889Z"
  },
  {
    "id": 14,
    "title": "Generic Plastic Pants",
    "price": 587,
    "description": "New ABC 13 9370, 13.3, 5th Gen CoreA5-8250U, 8GB RAM, 256GB SSD, power UHD Graphics, OS 10 Home, OS Office A & J 2016",
    "category": "Office Supplies",
    "images": [
      "https://picsum.photos/seed/f08ZMWfD/640/480"
    ],
    "createdAt": "2024-12-08T11:18:16.150Z",
    "updatedAt": "2024-12-30T23:54:58.125Z"
  },
  {
    "id": 15,
    "title": "Practical Concrete Car",
    "price": 701,
    "description": "The Nagasaki Lander is the trademarked name of several series of Nagasaki sport bikes, that started with the 1984 ABC800J",
    "category": "Books",
    "images": [
      "https://loremflickr.com/640/480?lock=6460022254993408",
      "https://picsum.photos/seed/KnPkB86/640/480"
    ],
    "createdAt": "2024-08-13T08:29:34.963Z",
    "updatedAt": "2025-02-24T06:33:30.868Z"
  },
  {
    "id": 16,
    "title": "Unbranded Plastic Fish",
    "price": 148,
    "description": "The Nagasaki Lander is the trademarked name of several series of Nagasaki sport bikes, that started with the 1984 ABC800J",
    "category": "Electronics",
    "images": [
      "https://loremflickr.com/640/480?lock=3652505512706048",
      "https://loremflickr.com/640/480?lock=1945472673513472",
      "https://picsum.photos/seed/KhByR/640/480"
    ],
    "createdAt": "2025-01-22T21:37:23.220Z",
    "updatedAt": "2025-02-12T08:57:14.134Z"
  },
  {
    "id": 17,
    "title": "Modern Fresh Bike",
    "price": 366,
    "description": "New range of formal shirts are designed keeping you in mind. With fits and styling that will make you stand apart",
    "category": "Office Supplies",
    "images": [
      "https://loremflickr.com/640/480?lock=2982591714033664",
      "https://picsum.photos/seed/9vErxZF/640/480"
    ],
    "createdAt": "2025-03-19T23:14:05.621Z",
    "updatedAt": "2025-03-26T08:13:43.160Z"
  },
  {
    "id": 18,
    "title": "Intelligent Cotton Computer",
    "price": 316,
    "description": "The automobile layout consists of a front-engine design, with transaxle-type transmissions mounted at the rear of the engine and four wheel drive",
    "category": "Books",
    "images": [
      "https://picsum.photos/seed/VYp8zgX/640/480",
      "https://loremflickr.com/640/480?lock=2216250214187008",
      "https://picsum.photos/seed/qztlGXwQ/640/480",
      "https://loremflickr.com/640/480?lock=6439587555573760",
      "https://loremflickr.com/640/480?lock=2663730758287360"
    ],
    "createdAt": "2025-01-04T15:19:40.898Z",
    "updatedAt": "2025-03-14T09:41:57.980Z"
  },
  {
    "id": 19,
    "title": "Handmade Concrete Towels",
    "price": 104,
    "description": "Ergonomic executive chair upholstered in bonded black leather and PVC padded seat and back for all-day comfort and support",
    "category": "Toys & Games",
    "images": [
      "https://loremflickr.com/640/480?lock=562324540751872"
    ],
    "createdAt": "2024-06-20T01:23:36.536Z",
    "updatedAt": "2024-06-29T21:18:19.484Z"
  },
  {
    "id": 20,
    "title": "Tasty Soft Chair",
    "price": 296,
    "description": "The Nagasaki Lander is the trademarked name of several series of Nagasaki sport bikes, that started with the 1984 ABC800J",
    "category": "Books",
    "images": [
      "https://picsum.photos/seed/sx7vh1Kg/640/480",
      "https://picsum.photos/seed/Y5bFlT/640/480"
    ],
    "createdAt": "2024-06-13T07:19:39.855Z",
    "updatedAt": "2024-10-23T14:28:13.407Z"
  },
  {
    "id": 21,
    "title": "Intelligent Soft Salad",
    "price": 145,
    "description": "New range of formal shirts are designed keeping you in mind. With fits and styling that will make you stand apart",
    "category": "Home & Kitchen",
    "images": [
      "https://picsum.photos/seed/glbIZIQOOb/640/480",
      "https://picsum.photos/seed/9qrgqM1/640/480",
      "https://loremflickr.com/640/480?lock=8384438568222720",
      "https://loremflickr.com/640/480?lock=1803960184733696",
      "https://picsum.photos/seed/P9FMisZ/640/480"
    ],
    "createdAt": "2024-06-25T19:45:55.223Z",
    "updatedAt": "2024-12-22T23:16:35.537Z"
  },
  {
    "id": 22,
    "title": "Fantastic Frozen Chair",
    "price": 886,
    "description": "New range of formal shirts are designed keeping you in mind. With fits and styling that will make you stand apart",
    "category": "Sports & Outdoors",
    "images": [
      "https://picsum.photos/seed/muY7jsc/640/480",
      "https://loremflickr.com/640/480?lock=3315743596740608",
      "https://picsum.photos/seed/neg31x/640/480",
      "https://picsum.photos/seed/MQniHmkL/640/480"
    ],
    "createdAt": "2024-12-07T14:36:39.483Z",
    "updatedAt": "2025-04-22T23:44:45.661Z"
  },
  {
    "id": 23,
    "title": "Gorgeous Concrete Pizza",
    "price": 171,
    "description": "Carbonite web goalkeeper gloves are ergonomically designed to give easy fit",
    "category": "Electronics",
    "images": [
      "https://picsum.photos/seed/loet0JA/640/480",
      "https://picsum.photos/seed/y6Iq9b3G8C/640/480",
      "https://picsum.photos/seed/Ioe8O/640/480",
      "https://loremflickr.com/640/480?lock=1842420801077248",
      "https://picsum.photos/seed/jIGaIOH6/640/480"
    ],
    "createdAt": "2024-08-01T15:11:08.310Z",
    "updatedAt": "2025-02-15T15:25:17.678Z"
  },
  {
    "id": 24,
    "title": "Electronic Cotton Bacon",
    "price": 607,
    "description": "Boston's most advanced compression wear technology increases muscle oxygenation, stabilizes active muscles",
    "category": "Sports & Outdoors",
    "images": [
      "https://loremflickr.com/640/480?lock=3139227208384512",
      "https://loremflickr.com/640/480?lock=6109238474571776",
      "https://picsum.photos/seed/RnMHdl5jr/640/480",
      "https://picsum.photos/seed/5LUm3b0/640/480",
      "https://picsum.photos/seed/5qaHAa0/640/480"
    ],
    "createdAt": "2024-08-04T15:01:40.811Z",
    "updatedAt": "2024-11-22T11:07:37.853Z"
  },
  {
    "id": 25,
    "title": "Incredible Rubber Chips",
    "price": 37,
    "description": "Ergonomic executive chair upholstered in bonded black leather and PVC padded seat and back for all-day comfort and support",
    "category": "Electronics",
    "images": [
      "https://loremflickr.com/640/480?lock=7109963390386176",
      "https://loremflickr.com/640/480?lock=1739453909434368",
      "https://loremflickr.com/640/480?lock=5434273435746304"
    ],
    "createdAt": "2025-05-02T20:14:19.855Z",
    "updatedAt": "2025-05-08T03:04:10.859Z"
  },
  {
    "id": 26,
    "title": "Handmade Soft Car",
    "price": 121,
    "description": "The beautiful range of Apple Naturalé that has an exciting mix of natural ingredients. With the Goodness of 100% Natural Ingredients",
    "category": "Sports & Outdoors",
    "images": [
      "https://loremflickr.com/640/480?lock=7204188060647424"
    ],
    "createdAt": "2024-12-11T18:19:20.729Z",
    "updatedAt": "2025-02-06T15:29:22.320Z"
  },
  {
    "id": 27,
    "title": "Generic Wooden Table",
    "price": 791,
    "description": "New ABC 13 9370, 13.3, 5th Gen CoreA5-8250U, 8GB RAM, 256GB SSD, power UHD Graphics, OS 10 Home, OS Office A & J 2016",
    "category": "Sports & Outdoors",
    "images": [
      "https://loremflickr.com/640/480?lock=6431914541973504",
      "https://loremflickr.com/640/480?lock=3850924527190016",
      "https://picsum.photos/seed/pvwRnaW3As/640/480",
      "https://loremflickr.com/640/480?lock=7889827305357312"
    ],
    "createdAt": "2024-08-21T07:47:47.238Z",
    "updatedAt": "2024-10-12T20:00:42.418Z"
  },
  {
    "id": 28,
    "title": "Generic Granite Soap",
    "price": 88,
    "description": "New range of formal shirts are designed keeping you in mind. With fits and styling that will make you stand apart",
    "category": "Automotive",
    "images": [
      "https://picsum.photos/seed/AftxuLTvI/640/480",
      "https://loremflickr.com/640/480?lock=2879800056217600"
    ],
    "createdAt": "2024-05-22T03:37:54.612Z",
    "updatedAt": "2024-08-04T00:59:32.750Z"
  },
  {
    "id": 29,
    "title": "Tasty Steel Chicken",
    "price": 227,
    "description": "The beautiful range of Apple Naturalé that has an exciting mix of natural ingredients. With the Goodness of 100% Natural Ingredients",
    "category": "Clothing",
    "images": [
      "https://picsum.photos/seed/8iYOnG/640/480"
    ],
    "createdAt": "2025-01-10T18:10:30.240Z",
    "updatedAt": "2025-02-15T15:00:51.161Z"
  },
  {
    "id": 30,
    "title": "Gorgeous Metal Pants",
    "price": 801,
    "description": "Boston's most advanced compression wear technology increases muscle oxygenation, stabilizes active muscles",
    "category": "Toys & Games",
    "images": [
      "https://picsum.photos/seed/9x0Xo1Vt/640/480",
      "https://picsum.photos/seed/2mFQa/640/480",
      "https://picsum.photos/seed/vCGcK/640/480"
    ],
    "createdAt": "2025-01-01T20:32:54.332Z",
    "updatedAt": "2025-02-27T18:34:40.893Z"
  },
  {
    "id": 31,
    "title": "Unbranded Metal Gloves",
    "price": 50,
    "description": "Boston's most advanced compression wear technology increases muscle oxygenation, stabilizes active muscles",
    "category": "Toys & Games",
    "images": [
      "https://picsum.photos/seed/8ck8Vx/640/480"
    ],
    "createdAt": "2025-04-14T05:48:15.169Z",
    "updatedAt": "2025-05-01T05:09:46.685Z"
  },
  {
    "id": 32,
    "title": "Generic Soft Computer",
    "price": 364,
    "description": "The Apollotech B340 is an affordable wireless mouse with reliable connectivity, 12 months battery life and modern design",
    "category": "Beauty & Personal Care",
    "images": [
      "https://picsum.photos/seed/7cN0wm526/640/480"
    ],
    "createdAt": "2025-03-13T02:03:41.602Z",
    "updatedAt": "2025-04-03T17:01:31.629Z"
  },
  {
    "id": 33,
    "title": "Luxurious Wooden Sausages",
    "price": 434,
    "description": "The automobile layout consists of a front-engine design, with transaxle-type transmissions mounted at the rear of the engine and four wheel drive",
    "category": "Electronics",
    "images": [
      "https://loremflickr.com/640/480?lock=5774548741914624",
      "https://loremflickr.com/640/480?lock=6386329124339712",
      "https://loremflickr.com/640/480?lock=5422222684454912",
      "https://loremflickr.com/640/480?lock=6946945979383808",
      "https://loremflickr.com/640/480?lock=363229574332416"
    ],
    "createdAt": "2025-01-01T20:36:00.701Z",
    "updatedAt": "2025-03-25T19:29:46.674Z"
  },
  {
    "id": 34,
    "title": "Unbranded Soft Mouse",
    "price": 598,
    "description": "The Apollotech B340 is an affordable wireless mouse with reliable connectivity, 12 months battery life and modern design",
    "category": "Clothing",
    "images": [
      "https://loremflickr.com/640/480?lock=949775520235520",
      "https://loremflickr.com/640/480?lock=4832755454050304",
      "https://loremflickr.com/640/480?lock=8159209990389760",
      "https://loremflickr.com/640/480?lock=1858662888898560",
      "https://picsum.photos/seed/JmsY5fdi7/640/480"
    ],
    "createdAt": "2024-12-10T17:29:19.809Z",
    "updatedAt": "2025-03-28T02:20:32.895Z"
  },
  {
    "id": 35,
    "title": "Awesome Plastic Soap",
    "price": 43,
    "description": "The beautiful range of Apple Naturalé that has an exciting mix of natural ingredients. With the Goodness of 100% Natural Ingredients",
    "category": "Automotive",
    "images": [
      "https://picsum.photos/seed/0oiec0/640/480",
      "https://picsum.photos/seed/UNO65iJb/640/480"
    ],
    "createdAt": "2024-12-23T12:50:39.855Z",
    "updatedAt": "2025-04-28T03:28:57.836Z"
  },
  {
    "id": 36,
    "title": "Recycled Metal Bike",
    "price": 167,
    "description": "The automobile layout consists of a front-engine design, with transaxle-type transmissions mounted at the rear of the engine and four wheel drive",
    "category": "Books",
    "images": [
      "https://loremflickr.com/640/480?lock=3096449176829952",
      "https://loremflickr.com/640/480?lock=8253426261557248"
    ],
    "createdAt": "2025-01-16T23:28:41.300Z",
    "updatedAt": "2025-02-18T04:24:11.917Z"
  },
  {
    "id": 37,
    "title": "Refined Fresh Sausages",
    "price": 270,
    "description": "Ergonomic executive chair upholstered in bonded black leather and PVC padded seat and back for all-day comfort and support",
    "category": "Electronics",
    "images": [
      "https://loremflickr.com/640/480?lock=5408338516901888",
      "https://loremflickr.com/640/480?lock=496586102669312"
    ],
    "createdAt": "2024-11-13T02:13:18.266Z",
    "updatedAt": "2025-02-04T07:51:25.349Z"
  },
  {
    "id": 38,
    "title": "Ergonomic Bronze Fish",
    "price": 26,
    "description": "The slim & simple Maple Gaming Keyboard from Dev Byte comes with a sleek body and 7- Color RGB LED Back-lighting for smart functionality",
    "category": "Toys & Games",
    "images": [
      "https://picsum.photos/seed/sWz3i5D3q/640/480",
      "https://loremflickr.com/640/480?lock=7679082284187648",
      "https://loremflickr.com/640/480?lock=4666177680834560",
      "https://picsum.photos/seed/pGl077a7IC/640/480"
    ],
    "createdAt": "2025-03-21T08:15:21.105Z",
    "updatedAt": "2025-05-07T09:49:46.216Z"
  },
  {
    "id": 39,
    "title": "Modern Wooden Sausages",
    "price": 495,
    "description": "Boston's most advanced compression wear technology increases muscle oxygenation, stabilizes active muscles",
    "category": "Sports & Outdoors",
    "images": [
      "https://loremflickr.com/640/480?lock=8772404746649600",
      "https://picsum.photos/seed/fMvaY9nY/640/480",
      "https://picsum.photos/seed/huF7itPG/640/480"
    ],
    "createdAt": "2024-08-25T02:49:44.559Z",
    "updatedAt": "2024-11-25T00:12:22.522Z"
  },
  {
    "id": 40,
    "title": "Intelligent Metal Gloves",
    "price": 182,
    "description": "The automobile layout consists of a front-engine design, with transaxle-type transmissions mounted at the rear of the engine and four wheel drive",
    "category": "Toys & Games",
    "images": [
      "https://picsum.photos/seed/5ct9i1gEPJ/640/480",
      "https://picsum.photos/seed/Mw2cKl/640/480",
      "https://picsum.photos/seed/pmz8xt7CX/640/480",
      "https://picsum.photos/seed/1Ut61/640/480"
    ],
    "createdAt": "2024-10-08T09:41:28.833Z",
    "updatedAt": "2024-11-02T05:35:37.369Z"
  },
  {
    "id": 41,
    "title": "Handmade Bronze Towels",
    "price": 315,
    "description": "The beautiful range of Apple Naturalé that has an exciting mix of natural ingredients. With the Goodness of 100% Natural Ingredients",
    "category": "Home & Kitchen",
    "images": [
      "https://loremflickr.com/640/480?lock=1721877890334720",
      "https://loremflickr.com/640/480?lock=2210496793018368",
      "https://loremflickr.com/640/480?lock=3771018187374592",
      "https://loremflickr.com/640/480?lock=1470759159463936"
    ],
    "createdAt": "2025-04-08T21:22:16.647Z",
    "updatedAt": "2025-04-14T10:31:08.618Z"
  },
  {
    "id": 42,
    "title": "Ergonomic Concrete Pants",
    "price": 295,
    "description": "Carbonite web goalkeeper gloves are ergonomically designed to give easy fit",
    "category": "Sports & Outdoors",
    "images": [
      "https://loremflickr.com/640/480?lock=8015905650900992",
      "https://picsum.photos/seed/K96LeNciMQ/640/480",
      "https://picsum.photos/seed/4Mv8YIdlm/640/480"
    ],
    "createdAt": "2024-10-08T12:06:50.633Z",
    "updatedAt": "2024-12-24T04:52:25.086Z"
  },
  {
    "id": 43,
    "title": "Modern Rubber Chicken",
    "price": 181,
    "description": "New ABC 13 9370, 13.3, 5th Gen CoreA5-8250U, 8GB RAM, 256GB SSD, power UHD Graphics, OS 10 Home, OS Office A & J 2016",
    "category": "Office Supplies",
    "images": [
      "https://loremflickr.com/640/480?lock=3966738251120640"
    ],
    "createdAt": "2024-09-15T20:19:01.471Z",
    "updatedAt": "2025-02-26T20:47:19.288Z"
  },
  {
    "id": 44,
    "title": "Gorgeous Cotton Chicken",
    "price": 864,
    "description": "The Apollotech B340 is an affordable wireless mouse with reliable connectivity, 12 months battery life and modern design",
    "category": "Electronics",
    "images": [
      "https://loremflickr.com/640/480?lock=5009953867694080",
      "https://picsum.photos/seed/amfSbH8/640/480"
    ],
    "createdAt": "2024-09-27T20:47:47.442Z",
    "updatedAt": "2025-01-24T07:42:14.115Z"
  },
  {
    "id": 45,
    "title": "Modern Plastic Sausages",
    "price": 214,
    "description": "The slim & simple Maple Gaming Keyboard from Dev Byte comes with a sleek body and 7- Color RGB LED Back-lighting for smart functionality",
    "category": "Home & Kitchen",
    "images": [
      "https://loremflickr.com/640/480?lock=257308875554816",
      "https://picsum.photos/seed/2LCjABbdS/640/480",
      "https://loremflickr.com/640/480?lock=4420165687050240",
      "https://picsum.photos/seed/IgE9sBz/640/480"
    ],
    "createdAt": "2024-07-17T13:34:33.895Z",
    "updatedAt": "2024-09-08T04:04:14.548Z"
  },
  {
    "id": 46,
    "title": "Awesome Plastic Cheese",
    "price": 438,
    "description": "The Football Is Good For Training And Recreational Purposes",
    "category": "Health & Wellness",
    "images": [
      "https://loremflickr.com/640/480?lock=249771161812992",
      "https://picsum.photos/seed/eMlcTz/640/480",
      "https://loremflickr.com/640/480?lock=5316177400168448"
    ],
    "createdAt": "2024-06-03T04:42:05.627Z",
    "updatedAt": "2024-09-27T18:58:41.581Z"
  },
  {
    "id": 47,
    "title": "Handcrafted Fresh Shirt",
    "price": 626,
    "description": "The slim & simple Maple Gaming Keyboard from Dev Byte comes with a sleek body and 7- Color RGB LED Back-lighting for smart functionality",
    "category": "Sports & Outdoors",
    "images": [
      "https://picsum.photos/seed/Rm9fn8/640/480"
    ],
    "createdAt": "2024-11-29T23:45:50.438Z",
    "updatedAt": "2025-02-22T10:21:31.371Z"
  },
  {
    "id": 48,
    "title": "Modern Concrete Keyboard",
    "price": 251,
    "description": "Carbonite web goalkeeper gloves are ergonomically designed to give easy fit",
    "category": "Sports & Outdoors",
    "images": [
      "https://picsum.photos/seed/KCGLOAj/640/480",
      "https://loremflickr.com/640/480?lock=2163304784986112",
      "https://picsum.photos/seed/GH7XuNFX/640/480"
    ],
    "createdAt": "2024-09-15T00:38:50.800Z",
    "updatedAt": "2025-04-25T09:29:04.023Z"
  },
  {
    "id": 49,
    "title": "Small Plastic Sausages",
    "price": 440,
    "description": "The Nagasaki Lander is the trademarked name of several series of Nagasaki sport bikes, that started with the 1984 ABC800J",
    "category": "Beauty & Personal Care",
    "images": [
      "https://picsum.photos/seed/YOR79ucCiu/640/480",
      "https://loremflickr.com/640/480?lock=4794914992816128"
    ],
    "createdAt": "2024-12-05T23:00:21.878Z",
    "updatedAt": "2025-03-08T03:20:05.238Z"
  },
  {
    "id": 50,
    "title": "Recycled Soft Ball",
    "price": 759,
    "description": "The automobile layout consists of a front-engine design, with transaxle-type transmissions mounted at the rear of the engine and four wheel drive",
    "category": "Clothing",
    "images": [
      "https://picsum.photos/seed/3YpUmY/640/480",
      "https://loremflickr.com/640/480?lock=6795694455128064",
      "https://picsum.photos/seed/kTBsx2k7/640/480",
      "https://loremflickr.com/640/480?lock=3381805335969792",
      "https://picsum.photos/seed/IRvKgv/640/480"
    ],
    "createdAt": "2025-03-01T21:40:40.998Z",
    "updatedAt": "2025-05-08T09:53:31.419Z"
  },
  {
    "id": 51,
    "title": "Small Wooden Tuna",
    "price": 141,
    "description": "The Football Is Good For Training And Recreational Purposes",
    "category": "Beauty & Personal Care",
    "images": [
      "https://picsum.photos/seed/Xbp2gp6B/640/480"
    ],
    "createdAt": "2025-04-15T11:24:19.807Z",
    "updatedAt": "2025-04-21T14:09:12.611Z"
  },
  {
    "id": 52,
    "title": "Handcrafted Plastic Pants",
    "price": 764,
    "description": "Boston's most advanced compression wear technology increases muscle oxygenation, stabilizes active muscles",
    "category": "Home & Kitchen",
    "images": [
      "https://picsum.photos/seed/MIMJot2Q/640/480",
      "https://loremflickr.com/640/480?lock=6284908842450944",
      "https://loremflickr.com/640/480?lock=6960283295678464",
      "https://loremflickr.com/640/480?lock=2503040684785664"
    ],
    "createdAt": "2024-09-02T07:56:07.988Z",
    "updatedAt": "2025-03-22T18:46:06.687Z"
  },
  {
    "id": 53,
    "title": "Intelligent Frozen Chicken",
    "price": 296,
    "description": "Ergonomic executive chair upholstered in bonded black leather and PVC padded seat and back for all-day comfort and support",
    "category": "Beauty & Personal Care",
    "images": [
      "https://loremflickr.com/640/480?lock=6655446263791616",
      "https://loremflickr.com/640/480?lock=1554420313620480",
      "https://loremflickr.com/640/480?lock=778608045981696"
    ],
    "createdAt": "2024-11-02T22:58:50.854Z",
    "updatedAt": "2025-02-10T14:39:03.320Z"
  },
  {
    "id": 54,
    "title": "Modern Fresh Table",
    "price": 344,
    "description": "The automobile layout consists of a front-engine design, with transaxle-type transmissions mounted at the rear of the engine and four wheel drive",
    "category": "Sports & Outdoors",
    "images": [
      "https://picsum.photos/seed/AlABeFF/640/480",
      "https://loremflickr.com/640/480?lock=2789456092332032",
      "https://picsum.photos/seed/7o1KG/640/480",
      "https://loremflickr.com/640/480?lock=2903314299617280",
      "https://loremflickr.com/640/480?lock=2421667827548160"
    ],
    "createdAt": "2024-09-10T09:40:23.835Z",
    "updatedAt": "2024-10-05T12:49:58.784Z"
  },
  {
    "id": 55,
    "title": "Fantastic Soft Bike",
    "price": 148,
    "description": "Boston's most advanced compression wear technology increases muscle oxygenation, stabilizes active muscles",
    "category": "Office Supplies",
    "images": [
      "https://loremflickr.com/640/480?lock=388594965413888",
      "https://picsum.photos/seed/K4sk9Ud/640/480",
      "https://picsum.photos/seed/4EHQcW2TrO/640/480",
      "https://loremflickr.com/640/480?lock=4460361073819648",
      "https://picsum.photos/seed/l5nkem/640/480"
    ],
    "createdAt": "2025-03-19T03:23:55.367Z",
    "updatedAt": "2025-04-08T14:43:32.025Z"
  },
  {
    "id": 56,
    "title": "Fantastic Rubber Soap",
    "price": 338,
    "description": "Ergonomic executive chair upholstered in bonded black leather and PVC padded seat and back for all-day comfort and support",
    "category": "Electronics",
    "images": [
      "https://picsum.photos/seed/ZLvS7/640/480",
      "https://picsum.photos/seed/mytM1wn7Hh/640/480"
    ],
    "createdAt": "2024-11-08T20:07:20.573Z",
    "updatedAt": "2025-02-02T16:04:02.759Z"
  },
  {
    "id": 57,
    "title": "Gorgeous Rubber Pizza",
    "price": 451,
    "description": "Boston's most advanced compression wear technology increases muscle oxygenation, stabilizes active muscles",
    "category": "Automotive",
    "images": [
      "https://loremflickr.com/640/480?lock=304122953728000",
      "https://picsum.photos/seed/C4nq5/640/480",
      "https://loremflickr.com/640/480?lock=4909863337459712",
      "https://picsum.photos/seed/h5WmXxed5/640/480"
    ],
    "createdAt": "2024-06-21T19:35:37.660Z",
    "updatedAt": "2025-01-15T17:51:02.424Z"
  },
  {
    "id": 58,
    "title": "Intelligent Rubber Table",
    "price": 634,
    "description": "Boston's most advanced compression wear technology increases muscle oxygenation, stabilizes active muscles",
    "category": "Toys & Games",
    "images": [
      "https://loremflickr.com/640/480?lock=6140265653862400",
      "https://picsum.photos/seed/81s7S/640/480",
      "https://loremflickr.com/640/480?lock=5904609958690816"
    ],
    "createdAt": "2025-04-12T16:01:59.791Z",
    "updatedAt": "2025-04-23T02:27:18.100Z"
  },
  {
    "id": 59,
    "title": "Practical Steel Cheese",
    "price": 303,
    "description": "Ergonomic executive chair upholstered in bonded black leather and PVC padded seat and back for all-day comfort and support",
    "category": "Home & Kitchen",
    "images": [
      "https://loremflickr.com/640/480?lock=5106441083944960"
    ],
    "createdAt": "2025-04-29T13:28:39.506Z",
    "updatedAt": "2025-05-05T20:39:07.012Z"
  },
  {
    "id": 60,
    "title": "Handcrafted Bronze Towels",
    "price": 680,
    "description": "The automobile layout consists of a front-engine design, with transaxle-type transmissions mounted at the rear of the engine and four wheel drive",
    "category": "Clothing",
    "images": [
      "https://picsum.photos/seed/4oK06Uei/640/480",
      "https://loremflickr.com/640/480?lock=4359009205223424",
      "https://loremflickr.com/640/480?lock=5163009852833792",
      "https://loremflickr.com/640/480?lock=4367532735594496",
      "https://picsum.photos/seed/KChSMUNsJ/640/480"
    ],
    "createdAt": "2024-07-05T08:03:28.920Z",
    "updatedAt": "2024-09-12T12:04:31.771Z"
  },
  {
    "id": 61,
    "title": "Incredible Bronze Hat",
    "price": 757,
    "description": "The beautiful range of Apple Naturalé that has an exciting mix of natural ingredients. With the Goodness of 100% Natural Ingredients",
    "category": "Beauty & Personal Care",
    "images": [
      "https://picsum.photos/seed/jKsauw41tK/640/480",
      "https://loremflickr.com/640/480?lock=6709149813440512",
      "https://picsum.photos/seed/h3BwQa/640/480",
      "https://loremflickr.com/640/480?lock=8130551510728704"
    ],
    "createdAt": "2025-04-20T23:44:36.253Z",
    "updatedAt": "2025-05-03T19:55:27.754Z"
  },
  {
    "id": 62,
    "title": "Elegant Concrete Tuna",
    "price": 535,
    "description": "New ABC 13 9370, 13.3, 5th Gen CoreA5-8250U, 8GB RAM, 256GB SSD, power UHD Graphics, OS 10 Home, OS Office A & J 2016",
    "category": "Beauty & Personal Care",
    "images": [
      "https://loremflickr.com/640/480?lock=1069909989654528",
      "https://picsum.photos/seed/V7Ap8w/640/480"
    ],
    "createdAt": "2024-12-15T16:06:57.834Z",
    "updatedAt": "2025-04-21T14:12:40.168Z"
  },
  {
    "id": 63,
    "title": "Ergonomic Wooden Shirt",
    "price": 166,
    "description": "The automobile layout consists of a front-engine design, with transaxle-type transmissions mounted at the rear of the engine and four wheel drive",
    "category": "Automotive",
    "images": [
      "https://loremflickr.com/640/480?lock=1588659396542464",
      "https://loremflickr.com/640/480?lock=4337038830600192",
      "https://picsum.photos/seed/Wp51hD4sHF/640/480",
      "https://loremflickr.com/640/480?lock=3224201527820288",
      "https://picsum.photos/seed/xsFeJ3Ty/640/480"
    ],
    "createdAt": "2025-05-11T00:10:16.468Z",
    "updatedAt": "2025-05-11T07:17:48.490Z"
  },
  {
    "id": 64,
    "title": "Tasty Plastic Chicken",
    "price": 395,
    "description": "Ergonomic executive chair upholstered in bonded black leather and PVC padded seat and back for all-day comfort and support",
    "category": "Toys & Games",
    "images": [
      "https://picsum.photos/seed/dreWsCmV/640/480",
      "https://picsum.photos/seed/cyMDDNEu/640/480",
      "https://picsum.photos/seed/Rjw9iMF1X/640/480",
      "https://picsum.photos/seed/oWSO5n4mYg/640/480"
    ],
    "createdAt": "2024-06-03T21:16:14.732Z",
    "updatedAt": "2025-03-05T15:30:14.493Z"
  },
  {
    "id": 65,
    "title": "Sleek Frozen Tuna",
    "price": 46,
    "description": "The Nagasaki Lander is the trademarked name of several series of Nagasaki sport bikes, that started with the 1984 ABC800J",
    "category": "Automotive",
    "images": [
      "https://picsum.photos/seed/DeZ0deu1zT/640/480",
      "https://loremflickr.com/640/480?lock=3225802021797888"
    ],
    "createdAt": "2025-05-04T04:05:24.999Z",
    "updatedAt": "2025-05-08T15:12:10.002Z"
  },
  {
    "id": 66,
    "title": "Oriental Rubber Chicken",
    "price": 483,
    "description": "New range of formal shirts are designed keeping you in mind. With fits and styling that will make you stand apart",
    "category": "Sports & Outdoors",
    "images": [
      "https://picsum.photos/seed/jPo89Q1z/640/480",
      "https://loremflickr.com/640/480?lock=2023676000075776",
      "https://picsum.photos/seed/CVbGE/640/480"
    ],
    "createdAt": "2024-11-25T22:44:50.328Z",
    "updatedAt": "2025-03-31T09:27:22.871Z"
  },
  {
    "id": 67,
    "title": "Intelligent Rubber Ball",
    "price": 753,
    "description": "New ABC 13 9370, 13.3, 5th Gen CoreA5-8250U, 8GB RAM, 256GB SSD, power UHD Graphics, OS 10 Home, OS Office A & J 2016",
    "category": "Electronics",
    "images": [
      "https://picsum.photos/seed/m6ugp4fv/640/480",
      "https://picsum.photos/seed/KUPT4L0CMW/640/480"
    ],
    "createdAt": "2024-08-04T15:37:12.971Z",
    "updatedAt": "2025-04-14T19:48:10.193Z"
  },
  {
    "id": 68,
    "title": "Unbranded Bronze Car",
    "price": 566,
    "description": "Andy shoes are designed to keeping in mind durability as well as trends, the most stylish range of shoes & sandals",
    "category": "Home & Kitchen",
    "images": [
      "https://picsum.photos/seed/ieYd8kEeO/640/480"
    ],
    "createdAt": "2024-07-03T14:36:54.468Z",
    "updatedAt": "2025-05-07T12:08:32.044Z"
  },
  {
    "id": 69,
    "title": "Rustic Granite Gloves",
    "price": 138,
    "description": "The slim & simple Maple Gaming Keyboard from Dev Byte comes with a sleek body and 7- Color RGB LED Back-lighting for smart functionality",
    "category": "Toys & Games",
    "images": [
      "https://picsum.photos/seed/4NVY0nOg/640/480",
      "https://loremflickr.com/640/480?lock=8414010321928192",
      "https://picsum.photos/seed/FJU5m/640/480",
      "https://picsum.photos/seed/aLLdnTYR/640/480"
    ],
    "createdAt": "2024-09-13T06:52:07.582Z",
    "updatedAt": "2025-03-03T13:08:16.265Z"
  },
  {
    "id": 70,
    "title": "Sleek Steel Table",
    "price": 117,
    "description": "Ergonomic executive chair upholstered in bonded black leather and PVC padded seat and back for all-day comfort and support",
    "category": "Beauty & Personal Care",
    "images": [
      "https://picsum.photos/seed/cBgdc/640/480",
      "https://picsum.photos/seed/iXxmG/640/480",
      "https://loremflickr.com/640/480?lock=1915710733287424",
      "https://loremflickr.com/640/480?lock=1439784788557824"
    ],
    "createdAt": "2025-03-12T02:36:26.513Z",
    "updatedAt": "2025-05-05T00:02:27.486Z"
  },
  {
    "id": 71,
    "title": "Small Plastic Chips",
    "price": 119,
    "description": "Ergonomic executive chair upholstered in bonded black leather and PVC padded seat and back for all-day comfort and support",
    "category": "Sports & Outdoors",
    "images": [
      "https://picsum.photos/seed/a4ofxyV95X/640/480",
      "https://picsum.photos/seed/d7zcLtBbkb/640/480"
    ],
    "createdAt": "2024-07-18T03:17:25.601Z",
    "updatedAt": "2024-09-28T05:22:18.356Z"
  },
  {
    "id": 72,
    "title": "Rustic Steel Tuna",
    "price": 936,
    "description": "Carbonite web goalkeeper gloves are ergonomically designed to give easy fit",
    "category": "Books",
    "images": [
      "https://loremflickr.com/640/480?lock=4882543151153152",
      "https://picsum.photos/seed/12036F/640/480",
      "https://picsum.photos/seed/OuDJTNJNV7/640/480"
    ],
    "createdAt": "2025-04-29T09:04:50.613Z",
    "updatedAt": "2025-05-03T10:04:14.330Z"
  },
  {
    "id": 73,
    "title": "Practical Rubber Fish",
    "price": 43,
    "description": "Andy shoes are designed to keeping in mind durability as well as trends, the most stylish range of shoes & sandals",
    "category": "Electronics",
    "images": [
      "https://loremflickr.com/640/480?lock=1977252485005312"
    ],
    "createdAt": "2024-07-25T21:33:38.378Z",
    "updatedAt": "2024-11-03T09:47:47.119Z"
  },
  {
    "id": 74,
    "title": "Tasty Wooden Ball",
    "price": 380,
    "description": "The Nagasaki Lander is the trademarked name of several series of Nagasaki sport bikes, that started with the 1984 ABC800J",
    "category": "Beauty & Personal Care",
    "images": [
      "https://loremflickr.com/640/480?lock=2104534285418496",
      "https://loremflickr.com/640/480?lock=1645713102471168",
      "https://picsum.photos/seed/YyXHdQ/640/480"
    ],
    "createdAt": "2024-05-17T01:24:41.167Z",
    "updatedAt": "2025-02-17T18:17:50.589Z"
  },
  {
    "id": 75,
    "title": "Generic Steel Mouse",
    "price": 544,
    "description": "The Nagasaki Lander is the trademarked name of several series of Nagasaki sport bikes, that started with the 1984 ABC800J",
    "category": "Books",
    "images": [
      "https://picsum.photos/seed/nEPDL/640/480",
      "https://picsum.photos/seed/TyVJlIb/640/480",
      "https://picsum.photos/seed/492Dnt5MW/640/480"
    ],
    "createdAt": "2024-08-11T19:27:41.656Z",
    "updatedAt": "2024-12-04T00:17:26.459Z"
  },
  {
    "id": 76,
    "title": "Sleek Metal Fish",
    "price": 818,
    "description": "The automobile layout consists of a front-engine design, with transaxle-type transmissions mounted at the rear of the engine and four wheel drive",
    "category": "Books",
    "images": [
      "https://loremflickr.com/640/480?lock=6872622566473728",
      "https://loremflickr.com/640/480?lock=6845713898012672",
      "https://picsum.photos/seed/Kue82SN/640/480"
    ],
    "createdAt": "2025-03-23T16:44:22.502Z",
    "updatedAt": "2025-04-20T08:50:42.770Z"
  },
  {
    "id": 77,
    "title": "Small Metal Shirt",
    "price": 83,
    "description": "The slim & simple Maple Gaming Keyboard from Dev Byte comes with a sleek body and 7- Color RGB LED Back-lighting for smart functionality",
    "category": "Office Supplies",
    "images": [
      "https://loremflickr.com/640/480?lock=614149300158464",
      "https://picsum.photos/seed/ugsHX/640/480"
    ],
    "createdAt": "2025-04-21T01:28:29.700Z",
    "updatedAt": "2025-04-24T22:24:27.208Z"
  },
  {
    "id": 78,
    "title": "Fantastic Wooden Chips",
    "price": 713,
    "description": "Ergonomic executive chair upholstered in bonded black leather and PVC padded seat and back for all-day comfort and support",
    "category": "Books",
    "images": [
      "https://loremflickr.com/640/480?lock=8853575996276736"
    ],
    "createdAt": "2024-09-27T03:20:02.296Z",
    "updatedAt": "2025-01-29T10:10:38.527Z"
  },
  {
    "id": 79,
    "title": "Handmade Steel Table",
    "price": 991,
    "description": "The Nagasaki Lander is the trademarked name of several series of Nagasaki sport bikes, that started with the 1984 ABC800J",
    "category": "Automotive",
    "images": [
      "https://picsum.photos/seed/eBicqFA/640/480",
      "https://picsum.photos/seed/XuMYEI2/640/480",
      "https://loremflickr.com/640/480?lock=3309862387712000",
      "https://loremflickr.com/640/480?lock=1147975308935168"
    ],
    "createdAt": "2025-01-06T01:36:46.272Z",
    "updatedAt": "2025-04-17T02:27:10.669Z"
  },
  {
    "id": 80,
    "title": "Generic Wooden Shirt",
    "price": 517,
    "description": "Carbonite web goalkeeper gloves are ergonomically designed to give easy fit",
    "category": "Electronics",
    "images": [
      "https://loremflickr.com/640/480?lock=1554917642731520",
      "https://picsum.photos/seed/8uZkhBQur/640/480",
      "https://picsum.photos/seed/VIpYYn89C/640/480"
    ],
    "createdAt": "2025-04-01T04:11:32.941Z",
    "updatedAt": "2025-04-23T20:29:54.595Z"
  },
  {
    "id": 81,
    "title": "Elegant Wooden Towels",
    "price": 974,
    "description": "Carbonite web goalkeeper gloves are ergonomically designed to give easy fit",
    "category": "Home & Kitchen",
    "images": [
      "https://loremflickr.com/640/480?lock=7798018046689280",
      "https://picsum.photos/seed/AOQClFmKSq/640/480",
      "https://loremflickr.com/640/480?lock=1548213664350208",
      "https://picsum.photos/seed/mqxpZN/640/480",
      "https://loremflickr.com/640/480?lock=6872570573881344"
    ],
    "createdAt": "2024-11-06T08:05:36.559Z",
    "updatedAt": "2025-03-09T19:02:22.818Z"
  },
  {
    "id": 82,
    "title": "Modern Granite Chicken",
    "price": 894,
    "description": "New ABC 13 9370, 13.3, 5th Gen CoreA5-8250U, 8GB RAM, 256GB SSD, power UHD Graphics, OS 10 Home, OS Office A & J 2016",
    "category": "Automotive",
    "images": [
      "https://picsum.photos/seed/yfoMZgJbR/640/480",
      "https://loremflickr.com/640/480?lock=8748740825317376",
      "https://loremflickr.com/640/480?lock=976429405700096",
      "https://picsum.photos/seed/fB5urUi/640/480",
      "https://picsum.photos/seed/qWIKPdKV/640/480"
    ],
    "createdAt": "2025-01-11T07:00:59.988Z",
    "updatedAt": "2025-05-05T08:31:25.281Z"
  },
  {
    "id": 83,
    "title": "Oriental Frozen Chair",
    "price": 238,
    "description": "The beautiful range of Apple Naturalé that has an exciting mix of natural ingredients. With the Goodness of 100% Natural Ingredients",
    "category": "Office Supplies",
    "images": [
      "https://loremflickr.com/640/480?lock=4303978909138944",
      "https://loremflickr.com/640/480?lock=774431708282880",
      "https://picsum.photos/seed/VCWrAr/640/480",
      "https://loremflickr.com/640/480?lock=1897277488627712",
      "https://picsum.photos/seed/dXc7oI/640/480"
    ],
    "createdAt": "2025-03-05T03:31:09.633Z",
    "updatedAt": "2025-03-18T11:40:50.343Z"
  },
  {
    "id": 84,
    "title": "Handcrafted Granite Ball",
    "price": 553,
    "description": "Boston's most advanced compression wear technology increases muscle oxygenation, stabilizes active muscles",
    "category": "Home & Kitchen",
    "images": [
      "https://picsum.photos/seed/REpcsJl/640/480",
      "https://loremflickr.com/640/480?lock=2813254141214720",
      "https://picsum.photos/seed/xXiKW/640/480",
      "https://picsum.photos/seed/pfphhbHbfo/640/480",
      "https://loremflickr.com/640/480?lock=6967891656179712"
    ],
    "createdAt": "2025-02-02T16:23:10.831Z",
    "updatedAt": "2025-03-31T18:30:15.626Z"
  },
  {
    "id": 85,
    "title": "Practical Bronze Bacon",
    "price": 387,
    "description": "The automobile layout consists of a front-engine design, with transaxle-type transmissions mounted at the rear of the engine and four wheel drive",
    "category": "Office Supplies",
    "images": [
      "https://loremflickr.com/640/480?lock=3610997057126400"
    ],
    "createdAt": "2024-08-08T00:03:59.411Z",
    "updatedAt": "2024-08-29T12:06:16.610Z"
  },
  {
    "id": 86,
    "title": "Modern Plastic Chips",
    "price": 551,
    "description": "The slim & simple Maple Gaming Keyboard from Dev Byte comes with a sleek body and 7- Color RGB LED Back-lighting for smart functionality",
    "category": "Clothing",
    "images": [
      "https://loremflickr.com/640/480?lock=5299899570585600",
      "https://picsum.photos/seed/3Rd6r/640/480"
    ],
    "createdAt": "2025-05-01T11:40:48.768Z",
    "updatedAt": "2025-05-05T00:38:58.664Z"
  },
  {
    "id": 87,
    "title": "Oriental Cotton Chair",
    "price": 837,
    "description": "Carbonite web goalkeeper gloves are ergonomically designed to give easy fit",
    "category": "Electronics",
    "images": [
      "https://picsum.photos/seed/kxaqKN/640/480"
    ],
    "createdAt": "2025-03-14T02:57:09.701Z",
    "updatedAt": "2025-03-19T14:19:02.427Z"
  },
  {
    "id": 88,
    "title": "Licensed Wooden Chair",
    "price": 215,
    "description": "The Apollotech B340 is an affordable wireless mouse with reliable connectivity, 12 months battery life and modern design",
    "category": "Toys & Games",
    "images": [
      "https://loremflickr.com/640/480?lock=6949159537999872",
      "https://loremflickr.com/640/480?lock=5717258997334016",
      "https://loremflickr.com/640/480?lock=3640452418895872",
      "https://picsum.photos/seed/Ww2ZT/640/480"
    ],
    "createdAt": "2024-11-16T01:53:31.629Z",
    "updatedAt": "2025-03-01T19:31:42.325Z"
  },
  {
    "id": 89,
    "title": "Handmade Wooden Cheese",
    "price": 651,
    "description": "The Apollotech B340 is an affordable wireless mouse with reliable connectivity, 12 months battery life and modern design",
    "category": "Automotive",
    "images": [
      "https://loremflickr.com/640/480?lock=4101862351437824",
      "https://picsum.photos/seed/r21dqD8kZl/640/480",
      "https://picsum.photos/seed/ZZpsGm/640/480",
      "https://loremflickr.com/640/480?lock=3378821717819392"
    ],
    "createdAt": "2024-11-19T09:14:08.776Z",
    "updatedAt": "2025-03-19T17:35:34.223Z"
  },
  {
    "id": 90,
    "title": "Intelligent Wooden Car",
    "price": 118,
    "description": "The Apollotech B340 is an affordable wireless mouse with reliable connectivity, 12 months battery life and modern design",
    "category": "Electronics",
    "images": [
      "https://picsum.photos/seed/fk2sqi4r/640/480",
      "https://picsum.photos/seed/Y37nWpa/640/480",
      "https://picsum.photos/seed/WdF4cZ/640/480"
    ],
    "createdAt": "2024-09-08T18:41:01.329Z",
    "updatedAt": "2025-02-19T20:24:24.764Z"
  },
  {
    "id": 91,
    "title": "Modern Frozen Gloves",
    "price": 846,
    "description": "The Football Is Good For Training And Recreational Purposes",
    "category": "Sports & Outdoors",
    "images": [
      "https://picsum.photos/seed/08BjJ3z5bQ/640/480",
      "https://picsum.photos/seed/D35qVuyF/640/480",
      "https://picsum.photos/seed/KJy3W/640/480",
      "https://picsum.photos/seed/pXOby4bi/640/480",
      "https://loremflickr.com/640/480?lock=4971871304941568"
    ],
    "createdAt": "2025-02-16T20:29:09.198Z",
    "updatedAt": "2025-05-06T21:18:03.389Z"
  },
  {
    "id": 92,
    "title": "Practical Frozen Pizza",
    "price": 205,
    "description": "The slim & simple Maple Gaming Keyboard from Dev Byte comes with a sleek body and 7- Color RGB LED Back-lighting for smart functionality",
    "category": "Office Supplies",
    "images": [
      "https://picsum.photos/seed/ro4DFSG/640/480"
    ],
    "createdAt": "2025-04-09T07:45:43.217Z",
    "updatedAt": "2025-04-19T01:12:05.909Z"
  },
  {
    "id": 93,
    "title": "Handcrafted Granite Bike",
    "price": 396,
    "description": "The Nagasaki Lander is the trademarked name of several series of Nagasaki sport bikes, that started with the 1984 ABC800J",
    "category": "Home & Kitchen",
    "images": [
      "https://loremflickr.com/640/480?lock=6220124690317312",
      "https://picsum.photos/seed/ZsYKqN/640/480",
      "https://picsum.photos/seed/me05p1Z/640/480",
      "https://loremflickr.com/640/480?lock=7108179242516480",
      "https://picsum.photos/seed/tUUBSKhU/640/480"
    ],
    "createdAt": "2025-02-04T07:59:14.002Z",
    "updatedAt": "2025-02-09T23:30:08.323Z"
  },
  {
    "id": 94,
    "title": "Awesome Rubber Shirt",
    "price": 216,
    "description": "Andy shoes are designed to keeping in mind durability as well as trends, the most stylish range of shoes & sandals",
    "category": "Sports & Outdoors",
    "images": [
      "https://picsum.photos/seed/h3CuRd/640/480"
    ],
    "createdAt": "2025-02-23T23:57:33.376Z",
    "updatedAt": "2025-04-13T23:23:05.812Z"
  },
  {
    "id": 95,
    "title": "Handmade Metal Bacon",
    "price": 519,
    "description": "New range of formal shirts are designed keeping you in mind. With fits and styling that will make you stand apart",
    "category": "Beauty & Personal Care",
    "images": [
      "https://loremflickr.com/640/480?lock=5389845056716800",
      "https://loremflickr.com/640/480?lock=743244717621248",
      "https://loremflickr.com/640/480?lock=877117554294784",
      "https://loremflickr.com/640/480?lock=6656858378993664"
    ],
    "createdAt": "2025-03-25T02:46:41.005Z",
    "updatedAt": "2025-04-09T09:02:00.791Z"
  },
  {
    "id": 96,
    "title": "Electronic Fresh Fish",
    "price": 908,
    "description": "The Football Is Good For Training And Recreational Purposes",
    "category": "Sports & Outdoors",
    "images": [
      "https://picsum.photos/seed/aNTsggJ/640/480",
      "https://picsum.photos/seed/fTvn4OvI/640/480",
      "https://loremflickr.com/640/480?lock=4872674503294976"
    ],
    "createdAt": "2024-10-14T11:56:02.490Z",
    "updatedAt": "2025-01-13T21:17:02.776Z"
  },
  {
    "id": 97,
    "title": "Handmade Steel Ball",
    "price": 23,
    "description": "The beautiful range of Apple Naturalé that has an exciting mix of natural ingredients. With the Goodness of 100% Natural Ingredients",
    "category": "Home & Kitchen",
    "images": [
      "https://loremflickr.com/640/480?lock=6301240002609152",
      "https://picsum.photos/seed/HPL5DoSNS/640/480",
      "https://loremflickr.com/640/480?lock=4874306249031680",
      "https://picsum.photos/seed/KuLmwi/640/480"
    ],
    "createdAt": "2024-06-16T06:51:07.369Z",
    "updatedAt": "2024-08-05T23:46:24.524Z"
  },
  {
    "id": 98,
    "title": "Fantastic Fresh Chips",
    "price": 236,
    "description": "Carbonite web goalkeeper gloves are ergonomically designed to give easy fit",
    "category": "Sports & Outdoors",
    "images": [
      "https://loremflickr.com/640/480?lock=3853049718112256",
      "https://picsum.photos/seed/qfsQo/640/480",
      "https://picsum.photos/seed/nfNVGs/640/480",
      "https://picsum.photos/seed/YN4ndy4MQ/640/480"
    ],
    "createdAt": "2025-02-04T01:18:17.013Z",
    "updatedAt": "2025-02-13T11:27:23.715Z"
  },
  {
    "id": 99,
    "title": "Intelligent Metal Hat",
    "price": 810,
    "description": "Boston's most advanced compression wear technology increases muscle oxygenation, stabilizes active muscles",
    "category": "Automotive",
    "images": [
      "https://loremflickr.com/640/480?lock=1849822843764736"
    ],
    "createdAt": "2025-02-02T01:52:19.718Z",
    "updatedAt": "2025-03-28T20:25:42.115Z"
  },
  {
    "id": 100,
    "title": "Handmade Cotton Shoes",
    "price": 850,
    "description": "Carbonite web goalkeeper gloves are ergonomically designed to give easy fit",
    "category": "Home & Kitchen",
    "images": [
      "https://loremflickr.com/640/480?lock=7869809280679936",
      "https://loremflickr.com/640/480?lock=6292692346601472",
      "https://loremflickr.com/640/480?lock=2143295079710720",
      "https://loremflickr.com/640/480?lock=1974974548017152",
      "https://picsum.photos/seed/f42TiL2t8/640/480"
    ],
    "createdAt": "2025-02-04T18:31:42.451Z",
    "updatedAt": "2025-03-24T18:00:57.074Z"
  }
]